CONTRIBUTING.rst
HISTORY.rst
LICENSE
MANIFEST.in
README.rst
setup.cfg
setup.py
arkesel_python/__init__.py
arkesel_python/arkesel_contacts.py
arkesel_python/arkesel_otp.py
arkesel_python/arkesel_sms.py
arkesel_python/cli.py
arkesel_python.egg-info/PKG-INFO
arkesel_python.egg-info/SOURCES.txt
arkesel_python.egg-info/dependency_links.txt
arkesel_python.egg-info/entry_points.txt
arkesel_python.egg-info/not-zip-safe
arkesel_python.egg-info/requires.txt
arkesel_python.egg-info/top_level.txt
docs/Makefile
docs/conf.py
docs/contributing.rst
docs/history.rst
docs/index.rst
docs/installation.rst
docs/make.bat
docs/readme.rst
docs/usage.rst
tests/__init__.py
tests/test_arkesel_contacts.py
tests/test_arkesel_otp.py
tests/test_arkesel_sms.py