Metadata-Version: 2.1
Name: arkesel-python
Version: 0.1.0
Summary: Python Library for the Arkesel API 
Home-page: https://github.com/wilham-lynce/arkesel_python
Author: Wilham Opoku Danquah
Author-email: wilhamlynce27@gmail.com
License: MIT license
Download-URL: https://github.com/wilham-lynce/arkesel_python/archive/refs/tags/0.1.0.tar.gz
Keywords: arkesel_python
Platform: UNKNOWN
Classifier: Development Status :: 2 - Pre-Alpha
Classifier: Intended Audience :: Developers
Classifier: License :: OSI Approved :: MIT License
Classifier: Natural Language :: English
Classifier: Programming Language :: Python :: 3
Classifier: Programming Language :: Python :: 3.6
Classifier: Programming Language :: Python :: 3.7
Classifier: Programming Language :: Python :: 3.8
Requires-Python: >=3.6
License-File: LICENSE
